masterful/__init__.py
masterful/architecture.py
masterful/constants.py
masterful/enums.py
masterful/evaluate.py
masterful/optimization.py
masterful/regularization.py
masterful/ssl.py
masterful/training.py
masterful/version.py
masterful/data/__init__.py
masterful/data/duplicate_detector.py
masterful/data/learner.py
masterful/data/params.py
masterful/data/converters/__init__.py
masterful/data/converters/scale/__init__.py
masterful/data/converters/scale/__main__.py
masterful/data/converters/scale/convert_annotations.py
masterful/data/converters/scale/convert_annotations_test.py
masterful/proto/__init__.py
masterful/proto/log_pb2.py
masterful/train/__init__.py
masterful/train/__main__.py
masterful/utils/__init__.py
masterful/utils/activate.py
masterful/utils/helpers.py
masterful-0.6.0.dist-info/LICENSE
masterful-0.6.0.dist-info/METADATA
masterful-0.6.0.dist-info/WHEEL
masterful-0.6.0.dist-info/entry_points.txt
masterful-0.6.0.dist-info/top_level.txt
masterful-0.6.0.dist-info/RECORD
